telemars/__init__.py
telemars/filters/__init__.py
telemars/filters/crosstab.py
telemars/filters/general.py
telemars/filters/simple.py
telemars/options/__init__.py
telemars/options/crosstab.py
telemars/options/gops.py
telemars/options/simple.py
telemars/params/__init__.py
telemars/params/filters/__init__.py
telemars/params/filters/crosstab.py
telemars/params/filters/general.py
telemars/params/filters/simple.py
telemars/params/options/__init__.py
telemars/params/options/crosstab.py
telemars/params/options/general.py
telemars/params/options/simple.py
telemars/params/slices/__init__.py
telemars/params/slices/crosstab.py
telemars/params/slices/simple.py
telemars/params/statistics/__init__.py
telemars/params/statistics/crosstab.py
telemars/params/statistics/simple.py
telemars/tasks/__init__.py
telemars/tasks/crosstab.py
telemars/tasks/simple.py
telemars/utils/__init__.py
telemars/utils/functools.py
telemars/utils/parser.py
telemars/utils/validators.py
telemars-0.1.7.dist-info/WHEEL
telemars-0.1.7.dist-info/METADATA
telemars-0.1.7.dist-info/RECORD
