Metadata-Version: 2.3
Name: telemars
Version: 0.1.7
Summary: telemars
Author: Aleksandr P.
Author-email: Aleksandr P. <prosvirnin.a@outlook.com>
Requires-Dist: mediascope-api-lib>=1.6.0
Requires-Dist: openpyxl>=3.1.5
Requires-Dist: polars>=1.34.0
Requires-Dist: pydantic>=2.11.10,<2.12
Requires-Dist: pytest>=8.4.2
Requires-Dist: pytest-asyncio>=1.2.0
Requires-Dist: xlsxwriter>=3.2.9
Requires-Python: >=3.12
